scarlet2/__init__.py
scarlet2/_version.py
scarlet2/bbox.py
scarlet2/fft.py
scarlet2/frame.py
scarlet2/init.py
scarlet2/interpolation.py
scarlet2/io.py
scarlet2/measure.py
scarlet2/module.py
scarlet2/morphology.py
scarlet2/nn.py
scarlet2/observation.py
scarlet2/plot.py
scarlet2/psf.py
scarlet2/renderer.py
scarlet2/scene.py
scarlet2/source.py
scarlet2/spectrum.py
scarlet2/wavelets.py
scarlet2-0.3.0.dist-info/licenses/LICENSE
scarlet2-0.3.0.dist-info/METADATA
scarlet2-0.3.0.dist-info/WHEEL
scarlet2-0.3.0.dist-info/top_level.txt
scarlet2-0.3.0.dist-info/RECORD
