Metadata-Version: 2.4
Name: scarlet2
Version: 0.3.0
Author-email: Peter Melchior <peter.m.melchior@gmail.com>
License: MIT License
Project-URL: Source Code, https://github.com/pmelchior/scarlet2
Classifier: Development Status :: 4 - Beta
Classifier: License :: OSI Approved :: MIT License
Classifier: Intended Audience :: Developers
Classifier: Intended Audience :: Science/Research
Classifier: Operating System :: OS Independent
Classifier: Programming Language :: Python
Requires-Python: >=3.10
License-File: LICENSE
Requires-Dist: equinox
Requires-Dist: jax
Requires-Dist: astropy
Requires-Dist: numpy
Requires-Dist: matplotlib
Requires-Dist: varname
Requires-Dist: optax
Requires-Dist: numpyro
Requires-Dist: h5py
Provides-Extra: dev
Requires-Dist: asv==0.6.4; extra == "dev"
Requires-Dist: huggingface_hub; extra == "dev"
Requires-Dist: jupyter; extra == "dev"
Requires-Dist: pre-commit; extra == "dev"
Requires-Dist: pytest; extra == "dev"
Requires-Dist: pytest-cov; extra == "dev"
Requires-Dist: ruff; extra == "dev"
Dynamic: license-file
